<!-- PS2 -->


<theme>
	<formatVersion>7</formatVersion>

	<view name="system">
	
		<image name="avatar1" extra="static">
			<origin>0 0</origin>									
			<size>0.3645833 1.0157407</size>									
			<pos>0.15 0.122</pos>
			<scale>0.65</scale>
			<opacity>0</opacity>
			<zIndex>19</zIndex>
			<path>./avatar1.png</path>
			<linearSmooth>true</linearSmooth>
		
			
			<storyboard repeat="forever">
					<animation property="opacity" from="0" to="1" begin="" duration="500" mode="linear"/>
					<animation property="x" to="0.23" begin="100" duration="3700" mode="EaseOut"/>
					<animation property="scale" from="0.65" to="0.95" begin="4000" duration="350" mode="bump"/>
					<animation property="x" to="0.333" begin="4000" duration="375" mode="EaseOut"/>
					<animation property="y" to="0.07" begin="4000" duration="375" mode="EaseOut"/>
					<animation property="scale" to="5" begin="9000" duration="1000" mode="Linear"/>
					<animation property="x" to="-0.2" begin="9000" duration="1000" mode="linear"/>
					<animation property="y" to="-0.8" begin="9000" duration="1000" mode="linear"/>
					<animation property="opacity" to="0" begin="9500" duration="500" mode="linear"/>
					
					<animation property="opacity" to="0" begin="32000" duration="100" mode="linear"/>
			</storyboard>
		</image>
		
		<image name="avatar2" extra="static">
			<origin>0 0</origin> 
			<size>0.3645833 1.0157407</size>
			<pos>0.15 0.122</pos>
			<scale>0.65</scale>
			<opacity>0</opacity>
			<path>./avatar2.png</path>
			<linearSmooth>true</linearSmooth>
			<zIndex>19</zIndex>
			
			<storyboard repeat="forever">
					<animation property="opacity" from="0" to="1" begin="11000" duration="500" mode="linear"/>
					<animation property="x" to="0.23" begin="11000" duration="3000" mode="EaseOut"/>
					<animation property="scale" from="0.65" to="0.95" begin="14000" duration="350" mode="bump"/>
					<animation property="x" to="0.345" begin="14000" duration="375" mode="EaseOut"/>
					<animation property="y" to="0.07" begin="14000" duration="375" mode="EaseOut"/>
					<animation property="scale" to="5" begin="19000" duration="1000" mode="Linear"/>
					<animation property="x" to="-0.2" begin="19000" duration="1000" mode="linear"/>
					<animation property="y" to="-0.8" begin="19000" duration="1000" mode="linear"/>
					<animation property="opacity" to="0" begin="19500" duration="500" mode="linear"/>
					
					<animation property="opacity" to="0" begin="32000" duration="100" mode="linear"/>
			</storyboard>
		</image>	
			
		
		<image name="avatar3" extra="static">
			<origin>0 0</origin> 
			<size>0.3645833 1.0157407</size>
			<pos>0.15 0.122</pos>
			<scale>0.65</scale>
			<opacity>0</opacity>
			<path>./avatar3.png</path>
			<linearSmooth>true</linearSmooth>
			<zIndex>19</zIndex>
			
			<storyboard repeat="forever">
					<animation property="opacity" from="0" to="1" begin="21000" duration="500" mode="linear"/>
					<animation property="x" to="0.23" begin="21000" duration="3000" mode="EaseOut"/>
					<animation property="scale" from="0.65" to="0.95" begin="24000" duration="350" mode="bump"/>
					<animation property="x" to="0.315" begin="24000" duration="375" mode="EaseOut"/>
					<animation property="y" to="0.07" begin="24000" duration="375" mode="EaseOut"/>
					<animation property="scale" to="5" begin="29000" duration="1000" mode="Linear"/>
					<animation property="x" to="-0.2" begin="29000" duration="1000" mode="linear"/>
					<animation property="y" to="-0.8" begin="29000" duration="1000" mode="linear"/>
					<animation property="opacity" to="0" begin="29500" duration="500" mode="linear"/>
					
					<animation property="opacity" to="0" begin="32000" duration="100" mode="linear"/>
			</storyboard>
		</image>	
		
		
		
		
		
		
		<image name="background2" extra="static">
			<origin>0.5 0.5</origin>									
		<size>0.58125 0.6509259</size>									
		<pos>0.3177083 0.3856481</pos>
			<opacity>0</opacity>
			<path>./background2.png</path>
			<zIndex>16</zIndex>
			
			
			
			<storyboard repeat="forever">
				<animation property="opacity" to="1" begin="4000" duration="15800" mode="linear"/>	
				<animation property="opacity" to="0" begin="21800" duration="8200" mode="linear"/>	
			</storyboard>
			
			
			
		</image>
		
		
		
	</view>

</theme>
