<!-- GB 2 Players -->

<theme>
	<formatVersion>7</formatVersion>

	<view name="system">
	
	
	
		<image name="avatar-run2" extra="static">
			<pos>-0.1 0.407</pos>
			<scale>0.5</scale>
			<path>./avatar-run2.png</path>
			<opacity>1</opacity>
			<rotation>5</rotation>
			<zIndex>17</zIndex>
			
			<storyboard repeat="forever">
				
				<animation property="x" to="0.42" begin="1000" duration="2800" mode="linear"/>
				
				<animation property="opacity" to="0" begin="1200" duration="50" mode="linear"/>
				<animation property="opacity" to="1" begin="1400" duration="50" mode="linear"/>
				<animation property="opacity" to="0" begin="1600" duration="50" mode="linear"/>
				<animation property="opacity" to="1" begin="1800" duration="50" mode="linear"/>
				<animation property="opacity" to="0" begin="2000" duration="50" mode="linear"/>
				<animation property="opacity" to="1" begin="2200" duration="50" mode="linear"/>
				<animation property="opacity" to="0" begin="2400" duration="50" mode="linear"/>
				<animation property="opacity" to="1" begin="2600" duration="50" mode="linear"/>
				<animation property="opacity" to="0" begin="2800" duration="50" mode="linear"/>
				<animation property="opacity" to="1" begin="3000" duration="50" mode="linear"/>
				<animation property="opacity" to="0" begin="3200" duration="50" mode="linear"/>
				<animation property="opacity" to="1" begin="3400" duration="50" mode="linear"/>
				<animation property="opacity" to="0" begin="3600" duration="50" mode="linear"/>
				<animation property="opacity" to="1" begin="3800" duration="50" mode="linear"/>
				
				<animation property="opacity" to="0" begin="3850" duration="50" mode="linear"/>
				<animation property="x" to="0.04" begin="3900" duration="50" mode="linear"/>
				
				<animation property="x" to="0.12" begin="5400" duration="400" mode="linear"/>
				<animation property="opacity" to="0" begin="5400" duration="50" mode="linear"/>
				<animation property="opacity" to="1" begin="5600" duration="50" mode="linear"/>
				<animation property="opacity" to="0" begin="5800" duration="50" mode="linear"/>
				
				
				
				
				<animation property="opacity" to="1" begin="20000" duration="1000" mode="linear"/>
			</storyboard>
		</image>		
	
	
	
		<image name="avatar-run" extra="static">
			
			<pos>-0.1 0.394</pos>
			
			
			<scale>0.5</scale>
			<path>./avatar-run.png</path>
			<opacity>1</opacity>
			<rotation>20</rotation>
			<zIndex>17</zIndex>
			
			<storyboard repeat="forever">
				
				<animation property="x" to="0.42" begin="1000" duration="2800" mode="linear"/>
				
				<animation property="opacity" to="1" begin="1200" duration="50" mode="linear"/>
				<animation property="opacity" to="0" begin="1400" duration="50" mode="linear"/>
				<animation property="opacity" to="1" begin="1600" duration="50" mode="linear"/>
				<animation property="opacity" to="0" begin="1800" duration="50" mode="linear"/>
				<animation property="opacity" to="1" begin="2000" duration="50" mode="linear"/>
				<animation property="opacity" to="0" begin="2200" duration="50" mode="linear"/>
				<animation property="opacity" to="1" begin="2400" duration="50" mode="linear"/>
				<animation property="opacity" to="0" begin="2600" duration="50" mode="linear"/>
				<animation property="opacity" to="1" begin="2800" duration="50" mode="linear"/>
				<animation property="opacity" to="0" begin="3000" duration="50" mode="linear"/>
				<animation property="opacity" to="1" begin="3200" duration="50" mode="linear"/>
				<animation property="opacity" to="0" begin="3400" duration="50" mode="linear"/>
				<animation property="opacity" to="1" begin="3600" duration="50" mode="linear"/>
				<animation property="opacity" to="0" begin="3800" duration="50" mode="linear"/>
				
				<animation property="opacity" to="0" begin="3850" duration="50" mode="linear"/>
				<animation property="x" to="0.04" begin="3900" duration="50" mode="linear"/>
				
				<animation property="x" to="0.12" begin="5400" duration="400" mode="linear"/>
				<animation property="opacity" to="1" begin="5400" duration="50" mode="linear"/>
				<animation property="opacity" to="0" begin="5600" duration="50" mode="linear"/>
				<animation property="opacity" to="1" begin="5800" duration="50" mode="linear"/>
				
				<animation property="opacity" to="0" begin="6000" duration="50" mode="linear"/>
				
				
				<animation property="opacity" to="1" begin="20000" duration="1000" mode="linear"/>
			</storyboard>
		</image>		
	
		
		
		<image name="avatar-run2_inverse" extra="static">
			<pos>0.42 0.39</pos>
			<scale>0.5</scale>
			<path>./avatar-run2_inverse.png</path>
			<opacity>0</opacity>
			<rotation>8</rotation>
			<zIndex>17</zIndex>
			
			<storyboard repeat="forever">
				
				<animation property="x" to="0.04" begin="3800" duration="1600" mode="linear"/>
				
				<animation property="opacity" to="1" begin="3800" duration="50" mode="linear"/>
				<animation property="opacity" to="0" begin="4000" duration="50" mode="linear"/>
				<animation property="opacity" to="1" begin="4200" duration="50" mode="linear"/>
				<animation property="opacity" to="0" begin="4400" duration="50" mode="linear"/>
				<animation property="opacity" to="1" begin="4600" duration="50" mode="linear"/>
				<animation property="opacity" to="0" begin="4800" duration="50" mode="linear"/>
				<animation property="opacity" to="1" begin="5000" duration="50" mode="linear"/>
				<animation property="opacity" to="0" begin="5200" duration="50" mode="linear"/>
				<animation property="opacity" to="1" begin="5400" duration="50" mode="linear"/>
				
				<animation property="opacity" to="0" begin="5450" duration="50" mode="linear"/>
				
				
				<animation property="opacity" to="1" begin="20000" duration="1000" mode="linear"/>
			</storyboard>
		</image>		
		
		<image name="avatar-run_inverse" extra="static">
			<pos>0.42 0.39</pos>
			<scale>0.5</scale>
			<path>./avatar-run_inverse.png</path>
			<opacity>0</opacity>
			<rotation>17</rotation>
			<zIndex>17</zIndex>
			
			<storyboard repeat="forever">
				
				<animation property="x" to="0.04" begin="3800" duration="1600" mode="linear"/>
				
				<animation property="opacity" to="0" begin="3800" duration="50" mode="linear"/>
				<animation property="opacity" to="1" begin="4000" duration="50" mode="linear"/>
				<animation property="opacity" to="0" begin="4200" duration="50" mode="linear"/>
				<animation property="opacity" to="1" begin="4400" duration="50" mode="linear"/>
				<animation property="opacity" to="0" begin="4600" duration="50" mode="linear"/>
				<animation property="opacity" to="1" begin="4800" duration="50" mode="linear"/>
				<animation property="opacity" to="0" begin="5000" duration="50" mode="linear"/>
				<animation property="opacity" to="1" begin="5200" duration="50" mode="linear"/>
				<animation property="opacity" to="0" begin="5400" duration="50" mode="linear"/>
				
				
				<animation property="opacity" to="1" begin="20000" duration="1000" mode="linear"/>
			</storyboard>
		</image>		
		
		
		
		<image name="avatar-stand" extra="static">
			<pos>0.12 0.413</pos>
			<scale>0.5</scale>
			<path>./avatar-stand.png</path>
			<opacity>0</opacity>
			<rotation>3</rotation>
			<zIndex>17</zIndex>
			
			<storyboard repeat="forever">
				
				
				<animation property="opacity" to="1" begin="6000" duration="50" mode="linear"/>
				
				
				<animation property="opacity" to="1" begin="20000" duration="1000" mode="linear"/>
			</storyboard>
			
		</image>
		
		
		<image name="avatar-general_jump" extra="static">
			<pos>1.1 -0.3</pos>
			<scale>1</scale>
			<path>./avatar-general_jump.png</path>
			<opacity>1</opacity>
			<rotation>3</rotation>
			<zIndex>17</zIndex>
			
			<storyboard repeat="forever">
			
				<animation property="x" to="0.5" begin="2800" duration="1000" mode="linear"/>
				<animation property="y" to="0.3" begin="2800" duration="1000" mode="bump"/>
				<animation property="scale" to="0.5" begin="2800" duration="1000" mode="linear"/>
				
				<animation property="y" to="0.374" begin="3800" duration="1000" mode="linear"/>
				<animation property="opacity" to="0" begin="4800" duration="50" mode="linear"/>
				
				<animation property="opacity" to="1" begin="20000" duration="1000" mode="linear"/>
			</storyboard>
			
		</image>
		
		
		
		<image name="avatar-general_stand" extra="static">
			<pos>0.5 0.377</pos>
			<scale>0.5</scale>
			<path>./avatar-general_stand.png</path>
			<opacity>0</opacity>
			<rotation>0</rotation>
			<zIndex>17</zIndex>
			
			<storyboard repeat="forever">
			
				<animation property="opacity" to="1" begin="4800" duration="50" mode="linear"/>
				
				<animation property="opacity" to="1" begin="20000" duration="1000" mode="linear"/>
				
			</storyboard>
			
		</image>
		
		
		
		
	
	
	
	
	
	
		<image name="bloc_jaune" extra="static">
			<pos>0.2 -0.1</pos>
			<scale>0.1</scale>
			<path>./bloc_jaune.png</path>
			<zIndex>14</zIndex>
			
			<storyboard repeat="forever">
				<animation property="y" from="-0.1" to="1" begin="1000" duration="2000" mode="linear"/>
				
				
				<animation property="opacity" to="1" begin="20000" duration="1000" mode="linear"/>				
			</storyboard>
		</image>		
		
		<image name="bloc_rouge" extra="static">
			<pos>0.35 -0.1</pos>
			<scale>0.1</scale>
			<path>./bloc_rouge.png</path>
			<zIndex>14</zIndex>
			
			<storyboard repeat="forever">
				<animation property="y" from="-0.1" to="1" begin="4000" duration="3000" mode="linear"/>
				
				
				<animation property="opacity" to="1" begin="20000" duration="1000" mode="linear"/>				
			</storyboard>
		</image>	
		
		
	
			
		<!-- <image name="bloc_bleu" extra="static"> -->
			<!-- <pos>0.27 -1</pos> -->
			<!-- <scale>0.4</scale> -->
			<!-- <path>./bloc_bleu.png</path> -->
			<!-- <zIndex>14</zIndex> -->
			
			<!-- <storyboard repeat="forever"> -->
				<!-- <animation property="y" from="-1" to="1.5" begin="2000" duration="3000" mode="linear"/> -->
				
				<!-- <animation property="rotation" to="50" begin="11000" duration="10" mode="linear"/> -->
				<!-- <animation property="scale" to="0.3" begin="11000" duration="10" mode="linear"/> -->
				<!-- <animation property="x" to="0.64" begin="11000" duration="" mode="linear"/> -->
				<!-- <animation property="y" from="-1" to="1.5" begin="11000" duration="3000" mode="linear"/> -->
				
				<!-- <animation property="rotation" to="-20" begin="22000" duration="10" mode="linear"/> -->
				<!-- <animation property="scale" to="0.5" begin="22000" duration="10" mode="linear"/> -->
				<!-- <animation property="x" to="0.33" begin="22000" duration="" mode="linear"/> -->
				<!-- <animation property="y" from="-1" to="1.5" begin="22000" duration="3000" mode="linear"/> -->
				
			<!-- </storyboard> -->
		<!-- </image>		 -->
		
	
		<!-- <image name="bloc_vert" extra="static"> -->
			<!-- <pos>0.04 -1</pos> -->
			<!-- <scale>0.3</scale> -->
			<!-- <path>./bloc_vert.png</path> -->
			<!-- <zIndex>14</zIndex> -->
			
			<!-- <storyboard repeat="forever"> -->
				<!-- <animation property="y" from="-1" to="1.5" begin="4000" duration="3000" mode="linear"/> -->
				
				<!-- <animation property="rotation" to="40" begin="13000" duration="10" mode="linear"/> -->
				<!-- <animation property="scale" to="0.2" begin="13000" duration="10" mode="linear"/> -->
				<!-- <animation property="x" to="0.77" begin="13000" duration="" mode="linear"/> -->
				<!-- <animation property="y" from="-1" to="1.5" begin="13000" duration="3000" mode="linear"/> -->
				
				<!-- <animation property="rotation" to="-60" begin="24000" duration="10" mode="linear"/> -->
				<!-- <animation property="scale" to="0.4" begin="24000" duration="10" mode="linear"/> -->
				<!-- <animation property="x" to="0.34" begin="24000" duration="" mode="linear"/> -->
				<!-- <animation property="y" from="-1" to="1.5" begin="24000" duration="3000" mode="linear"/> -->
				
			<!-- </storyboard> -->
		<!-- </image>		 -->
		
		
		<!-- <image name="bloc_orange" extra="static"> -->
			<!-- <pos>0.44 -1</pos> -->
			<!-- <scale>0.4</scale> -->
			<!-- <path>./bloc_vert.png</path> -->
			<!-- <zIndex>14</zIndex> -->
			
			<!-- <storyboard repeat="forever"> -->
				<!-- <animation property="y" from="-1" to="1.5" begin="6000" duration="3000" mode="linear"/> -->
				
				<!-- <animation property="rotation" to="90" begin="15000" duration="10" mode="linear"/> -->
				<!-- <animation property="scale" to="0.3" begin="15000" duration="10" mode="linear"/> -->
				<!-- <animation property="x" to="0.04" begin="15000" duration="" mode="linear"/> -->
				<!-- <animation property="y" from="-1" to="1.5" begin="15000" duration="3000" mode="linear"/> -->
				
				<!-- <animation property="rotation" to="-90" begin="27000" duration="10" mode="linear"/> -->
				<!-- <animation property="scale" to="0.2" begin="27000" duration="10" mode="linear"/> -->
				<!-- <animation property="x" to="0.68" begin="27000" duration="" mode="linear"/> -->
				<!-- <animation property="y" from="-1" to="1.5" begin="27000" duration="3000" mode="linear"/> -->
				
			<!-- </storyboard> -->
		<!-- </image>		 -->
		
		
		
		
		
		
		<image name="bloc_violet_flou" extra="static">
			<pos>0.44 -1</pos>
			<scale>0.8</scale>
			<path>./bloc_violet_flou.png</path>
			<zIndex>10</zIndex>
			
			<storyboard repeat="forever">
				<animation property="y" from="-1" to="1.5" begin="1000" duration="5000" mode="linear"/>
				
				<animation property="rotation" to="90" begin="19000" duration="10" mode="linear"/>
				<animation property="scale" to="1.1" begin="19000" duration="10" mode="linear"/>
				<animation property="x" to="0.04" begin="19000" duration="" mode="linear"/>
				<animation property="y" from="-1" to="1.5" begin="19000" duration="4000" mode="linear"/>
				
				<animation property="rotation" to="-90" begin="37000" duration="10" mode="linear"/>
				<animation property="scale" to="0.6" begin="37000" duration="10" mode="linear"/>
				<animation property="x" to="0.68" begin="37000" duration="" mode="linear"/>
				<animation property="y" from="-1" to="1.5" begin="37000" duration="2000" mode="linear"/>
				
			</storyboard>
		</image>		
		
		
		<image name="bloc_orange_flou" extra="static">
			<pos>0.64 -1</pos>
			<scale>1.1</scale>
			<path>./bloc_orange_flou.png</path>
			<zIndex>10</zIndex>
			
			<storyboard repeat="forever">
				<animation property="rotation" to="90" begin="4000" duration="10" mode="linear"/>
				<animation property="y" from="-1" to="1.5" begin="4000" duration="3000" mode="linear"/>
				
				<animation property="rotation" to="0" begin="22000" duration="10" mode="linear"/>
				<animation property="scale" to="0.8" begin="22000" duration="10" mode="linear"/>
				<animation property="x" to="0.34" begin="22000" duration="" mode="linear"/>
				<animation property="y" from="-1" to="1.5" begin="22000" duration="4000" mode="linear"/>
				
				<animation property="rotation" to="-90" begin="40000" duration="10" mode="linear"/>
				<animation property="scale" to="0.6" begin="40000" duration="10" mode="linear"/>
				<animation property="x" to="0.14" begin="40000" duration="" mode="linear"/>
				<animation property="y" from="-1" to="1.5" begin="40000" duration="2000" mode="linear"/>
				
			</storyboard>
		</image>		
		
		
		<image name="bloc_vert_flou" extra="static">
			<pos>0.24 -1</pos>
			<scale>0.8</scale>
			<path>./bloc_vert_flou.png</path>
			<zIndex>10</zIndex>
			
			<storyboard repeat="forever">
				<animation property="rotation" to="90" begin="7000" duration="10" mode="linear"/>
				<animation property="y" from="-1" to="1.5" begin="7000" duration="2000" mode="linear"/>
				
				<animation property="rotation" to="0" begin="25000" duration="10" mode="linear"/>
				<animation property="scale" to="1.1" begin="25000" duration="10" mode="linear"/>
				<animation property="x" to="0.74" begin="25000" duration="" mode="linear"/>
				<animation property="y" from="-1" to="1.5" begin="25000" duration="5000" mode="linear"/>
				
				<animation property="rotation" to="-90" begin="43000" duration="10" mode="linear"/>
				<animation property="scale" to="0.6" begin="43000" duration="10" mode="linear"/>
				<animation property="x" to="0.08" begin="43000" duration="" mode="linear"/>
				<animation property="y" from="-1" to="1.5" begin="43000" duration="3000" mode="linear"/>
				
			</storyboard>
		</image>		
		
		
		<image name="bloc_jaune_flou" extra="static">
			<pos>0.04 -1</pos>
			<scale>0.7</scale>
			<path>./bloc_jaune_flou.png</path>
			<zIndex>10</zIndex>
			
			<storyboard repeat="forever">
				<animation property="y" from="-1" to="1.5" begin="10000" duration="5000" mode="linear"/>
				
				<animation property="scale" to="0.8" begin="28000" duration="10" mode="linear"/>
				<animation property="x" to="0.24" begin="28000" duration="" mode="linear"/>
				<animation property="y" from="-1" to="1.5" begin="28000" duration="4000" mode="linear"/>
				
				<animation property="scale" to="1" begin="46000" duration="10" mode="linear"/>
				<animation property="x" to="0.54" begin="46000" duration="" mode="linear"/>
				<animation property="y" from="-1" to="0.7" begin="46000" duration="2000" mode="linear"/>
				
			</storyboard>
		</image>		
		
		<image name="bloc_rouge_flou" extra="static">
			<pos>0.24 -1</pos>
			<scale>1</scale>
			<path>./bloc_rouge_flou.png</path>
			<zIndex>10</zIndex>
			
			<storyboard repeat="forever">
				<animation property="y" from="-1" to="1.5" begin="13000" duration="3000" mode="linear"/>
				
				<animation property="rotation" to="-90" begin="31000" duration="10" mode="linear"/>
				<animation property="scale" to="0.6" begin="31000" duration="10" mode="linear"/>
				<animation property="x" to="0.64" begin="31000" duration="" mode="linear"/>
				<animation property="y" from="-1" to="1.5" begin="31000" duration="4000" mode="linear"/>
				
				<animation property="scale" to="0.8" begin="49000" duration="10" mode="linear"/>
				<animation property="x" to="0.04" begin="49000" duration="" mode="linear"/>
				<animation property="y" from="-1" to="1.5" begin="49000" duration="2000" mode="linear"/>
				
			</storyboard>
		</image>		
		
		<image name="bloc_bleu_flou" extra="static">
			<pos>0.24 -1</pos>
			<scale>0.5</scale>
			<path>./bloc_bleu_flou.png</path>
			<zIndex>10</zIndex>
			
			<storyboard repeat="forever">
				<animation property="y" from="-1" to="1.5" begin="16000" duration="5000" mode="linear"/>
				
				<animation property="scale" to="1" begin="34000" duration="10" mode="linear"/>
				<animation property="x" to="0.54" begin="34000" duration="" mode="linear"/>
				<animation property="y" from="-1" to="1.5" begin="34000" duration="3000" mode="linear"/>
				
				<animation property="scale" to="0.8" begin="52000" duration="10" mode="linear"/>
				<animation property="x" to="0.24" begin="52000" duration="" mode="linear"/>
				<animation property="y" from="-1" to="1.5" begin="52000" duration="2000" mode="linear"/>
				
			</storyboard>
		</image>		
		
	</view>

</theme>
