<!--
Theme: Animatix-DX for Retrobat / Batocera / Emuelec
author: Snapouille
license: creative commons CC-BY-NC-SA
originally based on: "carbon"
-->

<theme>
<formatVersion>7</formatVersion>
<view name="system">

<text name="system_description" extra="true">
<text>Lutro is an experimental lua game framework for libretro following the LÖVE API.</text>
</text>

<text name="system_description" extra="true" lang="fr">
<text>Lutro est un framework de jeu lua expérimental pour libretro suivant l'API LÖVE.</text>
</text>

<text name="system_description" extra="true" lang="de">
<text>Lutro ist ein experimentelles Lua-Spiel-Framework für libretro, das der LÖVE-API folgt.</text>
</text>

<text name="system_description" extra="true" lang="es">
<text>Lutro es un framework experimental de juegos en lua para libretro que sigue la API de LÖVE.</text>
</text>

<text name="system_description" extra="true" lang="it">
<text>Lutro è un framework di gioco lua sperimentale per libretro che segue le API di LÖVE.</text>
</text>

<text name="system_description" extra="true" lang="ja">
<text>Lutroは、LÖVE APIに従ったlibretro用の実験的なluaゲームフレームワークです。</text>
</text>

<text name="system_description" extra="true" lang="nl">
<text>Lutro is een experimenteel lua spelkader voor libretro dat de LÖVE API volgt.</text>
</text>

<text name="system_description" extra="true" lang="pl">
<text>Lutro to eksperymentalny framework do gier lua dla libretro podążający za LÖVE API.</text>
</text>

<text name="system_description" extra="true" lang="pt">
<text>Lutro é uma estrutura de jogo experimental de lua para o libretro seguindo o LÖVE API.</text>
</text>

<text name="system_description" extra="true" lang="ru">
<text>Lutro - это экспериментальный игровой фреймворк на языке lua для libretro, основанный на API LÖVE.</text>
</text>

</view>
</theme>
